greplica/__init__.py
greplica/__main__.py
greplica/grep.py
greplica-0.9.13.dist-info/LICENSE.md
greplica-0.9.13.dist-info/METADATA
greplica-0.9.13.dist-info/WHEEL
greplica-0.9.13.dist-info/entry_points.txt
greplica-0.9.13.dist-info/top_level.txt
greplica-0.9.13.dist-info/RECORD
